snet_contracts-1.0.1-py3.11-nspkg.pth
snet/contracts/__init__.py
snet/contracts/utils.py
snet/contracts/resources/abi/FetchToken.json
snet/contracts/resources/abi/MultiPartyEscrow.json
snet/contracts/resources/abi/Registry.json
snet/contracts/resources/abi/SingularityNetToken.json
snet/contracts/resources/abi/TokenConversionManager.json
snet/contracts/resources/abi/TokenConversionManagerV2.json
snet/contracts/resources/abi/TokenConversionManagerV3.json
snet/contracts/resources/abi/TokenStake.json
snet/contracts/resources/bytecode/FetchToken.json
snet/contracts/resources/bytecode/MultiPartyEscrow.json
snet/contracts/resources/bytecode/Registry.json
snet/contracts/resources/bytecode/SingularityNetToken.json
snet/contracts/resources/bytecode/TokenConversionManager.json
snet/contracts/resources/bytecode/TokenConversionManagerV2.json
snet/contracts/resources/bytecode/TokenConversionManagerV3.json
snet/contracts/resources/bytecode/TokenStake.json
snet/contracts/resources/networks/FetchToken.json
snet/contracts/resources/networks/MultiPartyEscrow.json
snet/contracts/resources/networks/Registry.json
snet/contracts/resources/networks/SingularityNetToken.json
snet/contracts/resources/networks/TokenStake.json
snet/contracts/resources/networks/converter/AGIX/TokenConversionManager.json
snet/contracts/resources/networks/converter/CGV/TokenConversionManager.json
snet/contracts/resources/networks/converter/NTX/TokenConversionManager.json
snet/contracts/resources/networks/converter/RJV/TokenConversionManager.json
snet_contracts-1.0.1.dist-info/licenses/LICENSE
snet_contracts-1.0.1.dist-info/METADATA
snet_contracts-1.0.1.dist-info/WHEEL
snet_contracts-1.0.1.dist-info/namespace_packages.txt
snet_contracts-1.0.1.dist-info/top_level.txt
snet_contracts-1.0.1.dist-info/RECORD
