Metadata-Version: 2.4
Name: snet-contracts
Version: 1.0.1
Summary: SingularityNET Ecosystem Contracts
Home-page: https://github.com/singnet/snet-ecosystem-contracts
Author: SingularityNET Foundation
Author-email: info@singularitynet.io
License: MIT
Requires-Python: >=3.10
License-File: LICENSE
Requires-Dist: web3>=7.0.0
Dynamic: author
Dynamic: author-email
Dynamic: description
Dynamic: description-content-type
Dynamic: home-page
Dynamic: license
Dynamic: license-file
Dynamic: requires-dist
Dynamic: requires-python
Dynamic: summary
